ct_segnet/measurements.py
ct_segnet/morpho.py
ct_segnet/seg_utils.py
ct_segnet/stats.py
ct_segnet/train_utils.py
ct_segnet/viewer.py
ct_segnet/data_utils/__init__.py
ct_segnet/data_utils/data_augmenter.py
ct_segnet/data_utils/data_io.py
ct_segnet/data_utils/patch_maker.py
ct_segnet/data_utils/patch_maker_3D.py
ct_segnet/model_utils/__init__.py
ct_segnet/model_utils/losses.py
ct_segnet/model_utils/models.py
ct_segnet-1.224.dist-info/LICENSE.md
ct_segnet-1.224.dist-info/METADATA
ct_segnet-1.224.dist-info/WHEEL
ct_segnet-1.224.dist-info/top_level.txt
ct_segnet-1.224.dist-info/RECORD
